{"id":212,"url":"https://myanimelist.net/anime/212/Project_A-Ko","images":{"image_url":"https://cdn.myanimelist.net/images/anime/2/58391.jpg","small_image_url":"https://cdn.myanimelist.net/images/anime/2/58391t.jpg","large_image_url":"https://cdn.myanimelist.net/images/anime/2/58391l.jpg"},"title_english":"Project A-Ko","title_japanese":"プロジェクトＡ子","status":"Finished Airing","popularity":4447,"synopsis":"Sixteen years after its destruction by a meteor, Graviton City has been rebuilt into a futuristic metropolis. However, this is of little concern to superpowered high school student Eiko Magami, who only cares about her best friend Shiiko Kotobuki and arriving at school on time. Unfortunately, the incredibly intelligent Biko Daitokuji intends to befriend Shiiko, taking Eiko's place as the Shiiko's best friend using any means she can. Biko decides that, to accomplish this, she must defeat Eiko in combat. In order to overcome her super strength and speed, Biko creates a mecha and challenges Eiko in front of their school gate. As the two commence their battle, an extremely large spaceship hovers over Earth, searching for something left behind. [Written by MAL Rewrite]","authors":null,"genres":["Action","Adventure","Comedy","Sci-Fi"]}